sqladmin_litestar_plugin/__init__.py
sqladmin_litestar_plugin/ext/__init__.py
sqladmin_litestar_plugin/ext/advanced_alchemy.py
sqladmin_litestar_plugin/py.typed
sqladmin_litestar_plugin-0.2.0.dist-info/LICENSE
sqladmin_litestar_plugin-0.2.0.dist-info/METADATA
sqladmin_litestar_plugin-0.2.0.dist-info/WHEEL
sqladmin_litestar_plugin-0.2.0.dist-info/RECORD
