Metadata-Version: 2.1
Name: sqladmin-litestar-plugin
Version: 0.2.0
Summary: 
Author: Peter Schutt
Author-email: peter.github@proton.me
Requires-Python: >=3.8,<4.0
Classifier: Programming Language :: Python :: 3
Classifier: Programming Language :: Python :: 3.8
Classifier: Programming Language :: Python :: 3.9
Classifier: Programming Language :: Python :: 3.10
Classifier: Programming Language :: Python :: 3.11
Classifier: Programming Language :: Python :: 3.12
Requires-Dist: litestar
Requires-Dist: sqladmin
Requires-Dist: typing-extensions
Requires-Dist: wtforms
